gitanalyzer/__init__.py
gitanalyzer/git.py
gitanalyzer/repository.py
gitanalyzer/domain/__init__.py
gitanalyzer/domain/commit.py
gitanalyzer/domain/developer.py
GitAnalyzer-1.0.0.dist-info/LICENSE
GitAnalyzer-1.0.0.dist-info/METADATA
GitAnalyzer-1.0.0.dist-info/WHEEL
GitAnalyzer-1.0.0.dist-info/top_level.txt
GitAnalyzer-1.0.0.dist-info/RECORD
